kong/exceptions.py
kong/__init__.py
kong/client.py
kong/simulator.py
kong/utils.py
kong/contract.py
kong/mixins.py
kong/compat.py
python_kong-0.4.0.dist-info/METADATA
python_kong-0.4.0.dist-info/top_level.txt
python_kong-0.4.0.dist-info/DESCRIPTION.rst
python_kong-0.4.0.dist-info/metadata.json
python_kong-0.4.0.dist-info/WHEEL
python_kong-0.4.0.dist-info/RECORD
