Metadata-Version: 2.0
Name: python-kong
Version: 0.4.0
Summary: A Python client for the Kong API (http://getkong.org/)
Home-page: https://github.com/vikingco/python-kong
Author: Dirk Moors
Author-email: dirk.moors@vikingco.com
License: BSD
Platform: UNKNOWN
Classifier: Development Status :: 3 - Alpha
Classifier: Intended Audience :: Developers
Classifier: License :: OSI Approved :: BSD License
Classifier: Operating System :: Unix
Classifier: Operating System :: POSIX
Classifier: Operating System :: Microsoft :: Windows
Classifier: Programming Language :: Python
Classifier: Programming Language :: Python :: 2.6
Classifier: Programming Language :: Python :: 2.7
Classifier: Programming Language :: Python :: 3
Classifier: Programming Language :: Python :: 3.3
Classifier: Programming Language :: Python :: 3.4
Classifier: Programming Language :: Python :: Implementation :: CPython
Classifier: Programming Language :: Python :: Implementation :: PyPy
Classifier: Topic :: Utilities
Requires-Dist: six (==1.9.0)
Requires-Dist: requests (==2.7.0)
Requires-Dist: ordereddict (==1.1)
Requires-Dist: backoff (==1.0.7)
